_chompjs.cp311-win32.pyd
chompjs/__init__.py
chompjs/chompjs.py
chompjs/py.typed
chompjs/test_parser.py
chompjs-1.4.0.dist-info/licenses/LICENSE
chompjs-1.4.0.dist-info/METADATA
chompjs-1.4.0.dist-info/WHEEL
chompjs-1.4.0.dist-info/top_level.txt
chompjs-1.4.0.dist-info/RECORD
