Metadata-Version: 2.1
Name: chompjs
Version: 1.4.0
Summary: Parsing JavaScript objects into Python dictionaries
Home-page: https://github.com/Nykakin/chompjs
Author: Mariusz Obajtek
Author-email: nykakin@gmail.com
Keywords: parsing parser JavaScript json json5 webscrapping
Classifier: Programming Language :: Python :: 3
Classifier: Programming Language :: JavaScript
Classifier: Intended Audience :: Developers
Classifier: License :: OSI Approved :: MIT License
Classifier: Operating System :: OS Independent
Classifier: Topic :: Software Development :: Libraries :: Python Modules
Classifier: Topic :: Text Processing :: General
Classifier: Topic :: Text Processing :: Linguistic
Classifier: Development Status :: 5 - Production/Stable
Classifier: Environment :: Console
Classifier: Environment :: Web Environment
Requires-Python: >=3.9
License-File: LICENSE
